odoo/addons/product_quantity_update_force_inventory/README.rst
odoo/addons/product_quantity_update_force_inventory/__init__.py
odoo/addons/product_quantity_update_force_inventory/__manifest__.py
odoo/addons/product_quantity_update_force_inventory/i18n/product_quantity_update_force_inventory.pot
odoo/addons/product_quantity_update_force_inventory/models/__init__.py
odoo/addons/product_quantity_update_force_inventory/models/product.py
odoo/addons/product_quantity_update_force_inventory/models/stock_quant.py
odoo/addons/product_quantity_update_force_inventory/readme/CONTRIBUTORS.rst
odoo/addons/product_quantity_update_force_inventory/readme/DESCRIPTION.rst
odoo/addons/product_quantity_update_force_inventory/static/description/icon.png
odoo/addons/product_quantity_update_force_inventory/static/description/index.html
odoo/addons/product_quantity_update_force_inventory/tests/__init__.py
odoo/addons/product_quantity_update_force_inventory/tests/test_stock_quant_editable_view_block.py
odoo/addons/product_quantity_update_force_inventory/views/product_views.xml
odoo14_addon_product_quantity_update_force_inventory-14.0.1.0.1.dist-info/METADATA
odoo14_addon_product_quantity_update_force_inventory-14.0.1.0.1.dist-info/WHEEL
odoo14_addon_product_quantity_update_force_inventory-14.0.1.0.1.dist-info/top_level.txt
odoo14_addon_product_quantity_update_force_inventory-14.0.1.0.1.dist-info/RECORD
